atlasplots/__init__.py
atlasplots/__version__.py
atlasplots/api.py
atlasplots/atlasstyle.py
atlasplots/core.py
atlasplots/root_helpers.py
atlasplots-0.1.11.dist-info/licenses/LICENSE
atlasplots-0.1.11.dist-info/METADATA
atlasplots-0.1.11.dist-info/WHEEL
atlasplots-0.1.11.dist-info/top_level.txt
atlasplots-0.1.11.dist-info/RECORD
