Metadata-Version: 2.4
Name: atlasplots
Version: 0.1.11
Summary: ATLAS Plots for Humans
Home-page: https://atlas-plots.readthedocs.io
Author: Joey Carter
Author-email: joey.carter@cern.ch
License: MIT
Project-URL: Documentation, https://atlas-plots.readthedocs.io/
Project-URL: Source, https://github.com/joeycarter/atlas-plots/
Classifier: Development Status :: 3 - Alpha
Classifier: Intended Audience :: Science/Research
Classifier: Natural Language :: English
Classifier: License :: OSI Approved :: MIT License
Classifier: Programming Language :: Python
Classifier: Programming Language :: Python :: 3
Classifier: Programming Language :: Python :: 3.6
Classifier: Programming Language :: Python :: 3.7
Classifier: Programming Language :: Python :: 3.8
Classifier: Programming Language :: Python :: Implementation :: CPython
Requires-Python: >=3.6
License-File: LICENSE
Requires-Dist: numpy>=1.18
Dynamic: author
Dynamic: author-email
Dynamic: classifier
Dynamic: description
Dynamic: description-content-type
Dynamic: home-page
Dynamic: license
Dynamic: license-file
Dynamic: project-url
Dynamic: requires-dist
Dynamic: requires-python
Dynamic: summary
